aqmlator/__init__.py
aqmlator/data_acquisition.py
aqmlator/data_preprocessing.py
aqmlator/database.py
aqmlator/qml.py
aqmlator/server.py
aqmlator/tuner.py
qbm4eo/__init__.py
qbm4eo/decoder.py
qbm4eo/encoder.py
qbm4eo/lbae.py
qbm4eo/rbm.py
aqmlator-0.2.0.dist-info/LICENSE.md
aqmlator-0.2.0.dist-info/METADATA
aqmlator-0.2.0.dist-info/WHEEL
aqmlator-0.2.0.dist-info/top_level.txt
aqmlator-0.2.0.dist-info/RECORD
