Metadata-Version: 2.2
Name: AQMLator
Version: 0.2.0
Summary: A package for auto quantum machine learning-izing your experiments!
Author: Tomasz Rybotycki
Author-email: Tomasz Rybotycki <rybotycki.tomasz+aqmlator@gmail.com>
License: Apache License 2.0.
Project-URL: documentation, https://aqmlator.readthedocs.io/en/latest/index.html
Project-URL: repository, https://github.com/Tomev/AQMLator
Classifier: Programming Language :: Python :: 3
Classifier: Intended Audience :: Science/Research
Classifier: License :: OSI Approved :: Apache Software License
Classifier: Natural Language :: English
Classifier: Operating System :: OS Independent
Classifier: Topic :: Scientific/Engineering
Classifier: Topic :: Scientific/Engineering :: Artificial Intelligence
Classifier: Topic :: Scientific/Engineering :: Physics
Requires-Python: >=3.11
License-File: LICENSE.md
Requires-Dist: requests
Requires-Dist: types-requests
Requires-Dist: scikit-learn
Requires-Dist: dill
Requires-Dist: pennylane==0.40.0
Requires-Dist: pennylane-qiskit==0.40.0
Requires-Dist: torch
Requires-Dist: torchvision
Requires-Dist: torchaudio
Requires-Dist: matplotlib
Requires-Dist: optuna
Requires-Dist: psycopg2-binary
Requires-Dist: optuna-dashboard
Requires-Dist: numpy
Requires-Dist: qiskit
Requires-Dist: qiskit-ibm-runtime
Requires-Dist: setuptools
Requires-Dist: lightning
Requires-Dist: lightning[extra]
Requires-Dist: scipy
Requires-Dist: dimod
Requires-Dist: tqdm
Requires-Dist: dwave-system
Requires-Dist: fastapi
Requires-Dist: uvicorn
Requires-Dist: pennylane-lightning
Dynamic: author
Dynamic: classifier
Dynamic: license
Dynamic: requires-dist
Dynamic: summary
